{
  "post_id": "1niq9qn",
  "title": "Pilot dies after plane carrying nearly 200kg of SpaceX-branded cocaine crashes in remote Brazil",
  "subreddit": "news",
  "url": "https://reddit.com/r/news/comments/1niq9qn/pilot_dies_after_plane_carrying_nearly_200kg_of/",
  "score": 2537,
  "comments": 202,
  "created_utc": 1758048838.0,
  "created_human": "2025-09-17 02:53:58",
  "image_url": null,
  "image_local_path": null,
  "meme_description": "Ah, the ol' SpaceX-branded cocaine delivery service, straight from the \"Elon Musk Express.\" I guess they were aiming for a high-flying business model, but ended up crashing and burning instead.",
  "upvote_rate": 16.719716935192285,
  "comment_rate": 0.0,
  "detected_at": "2025-09-17T20:44:57.333437",
  "package_created": "2025-09-17T20:44:57.333440"
}