{
  "post_id": "1nix2i1",
  "title": "Publishers Clearing House’s bankruptcy means ‘forever’ winners will no longer get paid",
  "subreddit": "news",
  "url": "https://reddit.com/r/news/comments/1nix2i1/publishers_clearing_houses_bankruptcy_means/",
  "score": 16710,
  "comments": 1065,
  "created_utc": 1758064748.0,
  "created_human": "2025-09-17 07:19:08",
  "image_url": "https://external-preview.redd.it/Oa38B_wi_ePj5n9AaXpyhl_Ual9ryG1hC8YYoRPkKfw.jpeg?auto=webp&s=a188658e166929c295f6a26f6e97f4466df13c33",
  "image_local_path": "images\\news_1nix2i1_1758115431.jpeg",
  "meme_description": "Well, there goes Publishers Clearing House crushing dreams like it's nothing.",
  "upvote_rate": 10.238068537862526,
  "comment_rate": 0.0,
  "detected_at": "2025-09-17T21:27:45.466420",
  "package_created": "2025-09-17T21:27:45.466424"
}